{"otherData": {},"traceEvents":[{"cat":"function","dur":39765,"name":"glfwInit","ph":"X","pid":0,"tid":1463402602,"ts":414491725684},{"cat":"function","dur":327613,"name":"glfwCreateWindow","ph":"X","pid":0,"tid":1463402602,"ts":414491765614},{"cat":"function","dur":5099,"name":"void __cdecl SLEngine::OpenGLContext::Init(void)","ph":"X","pid":0,"tid":1463402602,"ts":414492093405},{"cat":"function","dur":40,"name":"void __cdecl SLEngine::WindowsWindow::SetVSync(bool)","ph":"X","pid":0,"tid":1463402602,"ts":414492098567},{"cat":"function","dur":374431,"name":"void __cdecl SLEngine::WindowsWindow::Init(const struct SLEngine::WindowProps &)","ph":"X","pid":0,"tid":1463402602,"ts":414491724205},{"cat":"function","dur":374589,"name":"__cdecl SLEngine::WindowsWindow::WindowsWindow(const struct SLEngine::WindowProps &)","ph":"X","pid":0,"tid":1463402602,"ts":414491724204},{"cat":"function","dur":6,"name":"void __cdecl SLEngine::OpenGLRendererAPI::Init(void)","ph":"X","pid":0,"tid":1463402602,"ts":414492098867},{"cat":"function","dur":33,"name":"__cdecl SLEngine::OpenGLVertexArray::OpenGLVertexArray(void)","ph":"X","pid":0,"tid":1463402602,"ts":414492098902},{"cat":"function","dur":26,"name":"__cdecl SLEngine::OpenGLVertexBuffer::OpenGLVertexBuffer(float *,unsigned int)","ph":"X","pid":0,"tid":1463402602,"ts":414492098960},{"cat":"function","dur":0,"name":"void __cdecl SLEngine::OpenGLVertexBuffer::Bind(void) const","ph":"X","pid":0,"tid":1463402602,"ts":414492099277},{"cat":"function","dur":318,"name":"void __cdecl SLEngine::OpenGLVertexArray::AddVertexBuffer(const class std::shared_ptr<class SLEngine::VertexBuffer> &)","ph":"X","pid":0,"tid":1463402602,"ts":414492099015},{"cat":"function","dur":41,"name":"__cdecl SLEngine::OpenGLIndexBuffer::OpenGLIndexBuffer(unsigned int *,unsigned int)","ph":"X","pid":0,"tid":1463402602,"ts":414492099348},{"cat":"function","dur":0,"name":"void __cdecl SLEngine::OpenGLIndexBuffer::Bind(void) const","ph":"X","pid":0,"tid":1463402602,"ts":414492099411},{"cat":"function","dur":18,"name":"void __cdecl SLEngine::OpenGLVertexArray::SetIndexBuffer(const class std::shared_ptr<class SLEngine::IndexBuffer> &)","ph":"X","pid":0,"tid":1463402602,"ts":414492099409},{"cat":"function","dur":39,"name":"__cdecl SLEngine::OpenGLTexture2D::OpenGLTexture2D(unsigned int,unsigned int)","ph":"X","pid":0,"tid":1463402602,"ts":414492099451},{"cat":"function","dur":8,"name":"void __cdecl SLEngine::OpenGLTexture2D::SetData(void *,unsigned int)","ph":"X","pid":0,"tid":1463402602,"ts":414492099505},{"cat":"function","dur":182,"name":"class std::basic_string<char,struct std::char_traits<char>,class std::allocator<char> > __cdecl SLEngine::OpenGLShader::ReadFile(const class std::basic_string<char,struct std::char_traits<char>,class std::allocator<char> > &)","ph":"X","pid":0,"tid":1463402602,"ts":414492099534},{"cat":"function","dur":79,"name":"class std::unordered_map<unsigned int,class std::basic_string<char,struct std::char_traits<char>,class std::allocator<char> >,struct std::hash<unsigned int>,struct std::equal_to<unsigned int>,class std::allocator<struct std::pair<unsigned int const ,class std::basic_string<char,struct std::char_traits<char>,class std::allocator<char> > > > > __cdecl SLEngine::OpenGLShader::PreProcess(const class std::basic_string<char,struct std::char_traits<char>,class std::allocator<char> > &)","ph":"X","pid":0,"tid":1463402602,"ts":414492099741},{"cat":"function","dur":1552,"name":"void __cdecl SLEngine::OpenGLShader::Compile(const class std::unordered_map<unsigned int,class std::basic_string<char,struct std::char_traits<char>,class std::allocator<char> >,struct std::hash<unsigned int>,struct std::equal_to<unsigned int>,class std::allocator<struct std::pair<unsigned int const ,class std::basic_string<char,struct std::char_traits<char>,class std::allocator<char> > > > > &)","ph":"X","pid":0,"tid":1463402602,"ts":414492099839},{"cat":"function","dur":1926,"name":"__cdecl SLEngine::OpenGLShader::OpenGLShader(const class std::basic_string<char,struct std::char_traits<char>,class std::allocator<char> > &)","ph":"X","pid":0,"tid":1463402602,"ts":414492099533},{"cat":"function","dur":2,"name":"void __cdecl SLEngine::OpenGLShader::Bind(void) const","ph":"X","pid":0,"tid":1463402602,"ts":414492101525},{"cat":"function","dur":59,"name":"void __cdecl SLEngine::OpenGLShader::SetInt(const class std::basic_string<char,struct std::char_traits<char>,class std::allocator<char> > &,int)","ph":"X","pid":0,"tid":1463402602,"ts":414492101543},{"cat":"function","dur":2762,"name":"void __cdecl SLEngine::Renderer2D::Init(void)","ph":"X","pid":0,"tid":1463402602,"ts":414492098891},{"cat":"function","dur":2804,"name":"void __cdecl SLEngine::Renderer::Init(void)","ph":"X","pid":0,"tid":1463402602,"ts":414492098863},{"cat":"function","dur":843,"name":"void __cdecl SLEngine::ImGuiLayer::OnAttach(void)","ph":"X","pid":0,"tid":1463402602,"ts":414492101692},{"cat":"function","dur":883,"name":"void __cdecl SLEngine::Application::PushOverlay(class SLEngine::Layer *)","ph":"X","pid":0,"tid":1463402602,"ts":414492101686},{"cat":"function","dur":378393,"name":"__cdecl SLEngine::Application::Application(void)","ph":"X","pid":0,"tid":1463402602,"ts":414491724190},{"cat":"function","dur":1,"name":"__cdecl SLEngine::OrthographicCamera::OrthographicCamera(float,float,float,float)","ph":"X","pid":0,"tid":1463402602,"ts":414492102602},{"cat":"function","dur":169,"name":"stbi_load - OpenGLTexture2D::OpenGLTexture2D(const std:string&)","ph":"X","pid":0,"tid":1463402602,"ts":414492102624},{"cat":"function","dur":241,"name":"__cdecl SLEngine::OpenGLTexture2D::OpenGLTexture2D(const class std::basic_string<char,struct std::char_traits<char>,class std::allocator<char> > &)","ph":"X","pid":0,"tid":1463402602,"ts":414492102624},{"cat":"function","dur":267,"name":"void __cdecl Sandbox2D::OnAttach(void)","ph":"X","pid":0,"tid":1463402602,"ts":414492102622},{"cat":"function","dur":283,"name":"void __cdecl SLEngine::Application::PushLayer(class SLEngine::Layer *)","ph":"X","pid":0,"tid":1463402602,"ts":414492102618}]}